processing/__init__.py
processing/batch/__init__.py
processing/batch/dwell_time.py
processing/batch/reconstruct.py
processing/core/__init__.py
processing/core/recon.py
processing/export/__init__.py
processing/export/export.py
processing/files/__init__.py
processing/files/files.py
processing/libs/__init__.py
processing/libs/ffmpeg.exe
processing/libs/imagecalculator.py
processing/libs/waveform.py
processing/plots/__init__.py
processing/plots/plots.py
endopy_ppp-0.1.1.dist-info/WHEEL
endopy_ppp-0.1.1.dist-info/METADATA
endopy_ppp-0.1.1.dist-info/RECORD
