Metadata-Version: 2.1
Name: endopy-ppp
Version: 0.1.1
Summary: Public source files for Endopy data post processing. Written in Python 3.
License: Proprietary
Author: jysru
Author-email: jysru@pm.me
Requires-Python: >=3.11,<4.0
Classifier: License :: Other/Proprietary License
Classifier: Programming Language :: Python :: 3
Classifier: Programming Language :: Python :: 3.11
Requires-Dist: configparser (>=5.3.0,<6.0.0)
Requires-Dist: matplotlib (>=3.6.2,<4.0.0)
Requires-Dist: numpy (>=1.23.5,<2.0.0)
Requires-Dist: scipy (>=1.9.3,<2.0.0)
Requires-Dist: tifffile (>=2022.10.10,<2023.0.0)
